batou/__init__.py
batou/_output.py
batou/agent.py
batou/c.py
batou/component.py
batou/conftest.py
batou/deploy.py
batou/environment.py
batou/fixtures.py
batou/host.py
batou/insecure-private.key
batou/main.py
batou/provision.py
batou/remote_core.py
batou/repository.py
batou/resources.py
batou/template.py
batou/utils.py
batou/version.txt
batou/vfs.py
batou/init-template/.hgignore
batou/init-template/components/example/component.py
batou/init-template/environments/dev.cfg
batou/lib/__init__.py
batou/lib/appenv.py
batou/lib/archive.py
batou/lib/buildout.py
batou/lib/cmmi.py
batou/lib/cron.py
batou/lib/debian.py
batou/lib/download.py
batou/lib/file.py
batou/lib/git.py
batou/lib/goceptnet.py
batou/lib/logrotate.py
batou/lib/mercurial.py
batou/lib/mysql.py
batou/lib/nagios.py
batou/lib/package.py
batou/lib/python.py
batou/lib/service.py
batou/lib/supervisor.py
batou/lib/svn.py
batou/lib/resources/check_supervisor.py.in
batou/lib/resources/crontab
batou/lib/resources/init.sh
batou/lib/resources/logrotate.in
batou/lib/resources/nagios.cfg
batou/lib/resources/nrpe.cfg
batou/lib/resources/supervisor.buildout.cfg
batou/lib/resources/supervisor.conf
batou/lib/tests/__init__.py
batou/lib/tests/test_appenv.py
batou/lib/tests/test_archive.py
batou/lib/tests/test_buildout.py
batou/lib/tests/test_cmmi.py
batou/lib/tests/test_cron.py
batou/lib/tests/test_debian.py
batou/lib/tests/test_download.py
batou/lib/tests/test_file.py
batou/lib/tests/test_git.py
batou/lib/tests/test_mercurial.py
batou/lib/tests/test_mysql.py
batou/lib/tests/test_nagios.py
batou/lib/tests/test_python.py
batou/lib/tests/test_service.py
batou/lib/tests/test_supervisor.py
batou/lib/tests/test_svn.py
batou/migrate/__init__.py
batou/migrate/migrations/2300.py
batou/migrate/migrations/2301.py
batou/migrate/migrations/2302.py
batou/migrate/migrations/2303.py
batou/migrate/migrations/2400.py
batou/migrate/migrations/__init__.py
batou/migrate/tests/__init__.py
batou/migrate/tests/test_migrate.py
batou-2.6.1.dist-info/LICENSE.txt
batou-2.6.1.dist-info/METADATA
batou-2.6.1.dist-info/WHEEL
batou-2.6.1.dist-info/entry_points.txt
batou-2.6.1.dist-info/top_level.txt
batou-2.6.1.dist-info/RECORD
