Metadata-Version: 2.1
Name: batou
Version: 2.6.1
Summary: A utility for automating multi-host, multi-environment software builds and deployments.
Home-page: https://batou.readthedocs.io/en/latest/
Author: Christian Theune
Author-email: ct@flyingcircus.io
License: BSD (2-clause)
Keywords: deployment
Classifier: License :: OSI Approved :: BSD License
Classifier: Programming Language :: Python
Classifier: Programming Language :: Python :: 3
Classifier: Programming Language :: Python :: 3.6
Classifier: Programming Language :: Python :: 3.7
Classifier: Programming Language :: Python :: 3.8
Classifier: Programming Language :: Python :: 3.9
Classifier: Programming Language :: Python :: 3 :: Only
Requires-Python: >=3.6
License-File: LICENSE.txt
Requires-Dist: ConfigUpdater >=3.2
Requires-Dist: Jinja2 >=3.1.4
Requires-Dist: requests
Requires-Dist: setuptools >=66.1.0
Requires-Dist: execnet >=1.8.1
Requires-Dist: importlib-metadata
Requires-Dist: importlib-resources
Requires-Dist: py >=1.11.0
Requires-Dist: pyyaml
Requires-Dist: remote-pdb
Provides-Extra: test
Requires-Dist: mock ; extra == 'test'
Requires-Dist: pytest ; extra == 'test'
Requires-Dist: pytest-coverage ; extra == 'test'
Requires-Dist: pytest-instafail ; extra == 'test'
Requires-Dist: pytest-timeout ; extra == 'test'
